{
  "id": "FT538940",
  "type": "mcq",
  "title": "China leaders get authority from being Gen. Sec.",
  "content": {
    "description": "",
    "question": "Chinese leaders Hu Jintao and Jiang Zemin gained their political authority and effective political power from which of the following?",
    "image": null,
    "choices": [
      {
        "label": "Their position as president or head of state",
        "image": null
      },
      {
        "label": "The process of popular election",
        "image": null
      },
      {
        "label": "Their close ties with former Soviet leaders",
        "image": null
      },
      {
        "label": "The power, prestige, and wealth of their families in the precommunist era",
        "image": null
      },
      {
        "label": "Their position as general secretary",
        "image": null
      }
    ],
    "answer": "Their position as general secretary"
  },
  "unit": {
    "code": "2",
    "text": "2: Political Institutions"
  },
  "topic": {
    "code": "2.3",
    "text": "2.3: Executive Systems"
  },
  "skill": {
    "code": "Skill 1.D",
    "text": "Skill 1.D: Describe political systems, principles, institutions, processes, policies, and behaviors of a course country."
  }
}