{
  "id": "VH920215",
  "type": "mcq",
  "title": "Devolution in the UK",
  "content": {
    "description": "",
    "question": "Which of the following best explains the “elephant in the room” as expressed in the passage?",
    "image": null,
    "choices": [
      {
        "label": "There is a lack of transparent political processes as far as the national question is concerned.",
        "image": null
      },
      {
        "label": "Scotland, Wales, and Northern Ireland have been granted assemblies, whereas England has none.",
        "image": null
      },
      {
        "label": "There is a likelihood that Scotland will have to leave the United Kingdom if these behaviors continue.",
        "image": null
      },
      {
        "label": "The English have an overwhelming majority in the House of Commons.",
        "image": null
      }
    ],
    "answer": "Scotland, Wales, and Northern Ireland have been granted assemblies, whereas England has none."
  },
  "unit": {
    "code": "1",
    "text": "1: Political Systems, Regimes, and Governments"
  },
  "topic": {
    "code": "1.7",
    "text": "1.7: Federal and Unitary Systems"
  },
  "skill": {
    "code": "Skill 4.B",
    "text": "Skill 4.B: Explain how the author's argument or perspective relates to political systems, principles, institutions, processes, policies, and behaviors."
  }
}