{
  "id": "VH975331",
  "type": "mcq",
  "title": "Salmorejo 2",
  "content": {
    "description": "",
    "question": "Según la presentación, ¿cómo se usa el pan en este plato?",
    "image": null,
    "choices": [
      {
        "label": "Se sirve en rodajas tostadas para acompañarlo.",
        "image": null
      },
      {
        "label": "Se corta en trozos y se usa para decorarlo.",
        "image": null
      },
      {
        "label": "Se deja ablandar en la crema antes de batirla.",
        "image": null
      },
      {
        "label": "Se raya bien fino y se agrega de a poco a la crema.",
        "image": null
      }
    ],
    "answer": "Se deja ablandar en la crema antes de batirla."
  },
  "unit": {
    "code": "5",
    "text": "5: Factors That Impact the Quality of Life"
  },
  "skill": {
    "code": "Skill 2.B",
    "text": "Skill 2.B: Make connections in and across disciplines."
  }
}