{
  "id": "VR033723",
  "type": "mcq",
  "title": "Bibliotecas en Colombia 4",
  "content": {
    "description": "",
    "question": "Según la entrevista, ¿por qué el entrevistado presta gratis los libros?",
    "image": null,
    "choices": [
      {
        "label": "Porque no necesita el dinero",
        "image": null
      },
      {
        "label": "Porque quiere ayudar a los necesitados",
        "image": null
      },
      {
        "label": "Porque ni él ni su esposa trabajan",
        "image": null
      },
      {
        "label": "Porque desea hacerse famoso",
        "image": null
      }
    ],
    "answer": "Porque quiere ayudar a los necesitados"
  },
  "unit": {
    "code": "3",
    "text": "3: Influences of Beauty and Art"
  },
  "skill": {
    "code": "Skill 1.A",
    "text": "Skill 1.A: Describe the literal meaning of the text."
  }
}