{
  "id": "AY224574",
  "type": "mcq",
  "title": "Explaining low voter turnout",
  "content": {
    "description": "",
    "question": "Which of the following is NOT an explanation for low voter turnout?",
    "image": null,
    "choices": [
      {
        "label": "Registration requirements",
        "image": null
      },
      {
        "label": "Low political efficacy among many voters",
        "image": null
      },
      {
        "label": "Laws protecting minority voting rights",
        "image": null
      },
      {
        "label": "Frequent elections at the state and local level",
        "image": null
      },
      {
        "label": "Weekday elections",
        "image": null
      }
    ],
    "answer": "Laws protecting minority voting rights"
  },
  "unit": {
    "code": "5",
    "text": "5: Political Participation"
  },
  "topic": {
    "code": "5.2",
    "text": "5.2: Voter Turnout"
  },
  "skill": {
    "code": "Skill 1.A",
    "text": "Skill 1.A: Describe political principles, institutions, processes, policies, and behaviors."
  }
}