{
  "id": "VH955527",
  "type": "mcq",
  "title": "Executive Orders by party",
  "content": {
    "description": "EXECUTIVE ORDERS 1945—2016\n\nSource: The American Presidency Project at University of California Santa Barbara, 2016",
    "question": "Which of the following statements is supported by the data in the information graphic?",
    "image": "https://cdn.jsdelivr.net/gh/hearingmeout/Images-Shard-2@latest/United_States_Government_and_Politics/2bc81d4bfeb00473837e9e31c02118bf.png",
    "choices": [
      {
        "label": "The use of executive orders has increased since 1945.",
        "image": null
      },
      {
        "label": "Democratic presidents issued more executive orders than Republican presidents did between 1945 and 2016.",
        "image": null
      },
      {
        "label": "The use of executive orders peaked in the 1970s and has since decreased.",
        "image": null
      },
      {
        "label": "Presidents have tended to prefer executive orders to signing statements since 1945.",
        "image": null
      }
    ],
    "answer": "Democratic presidents issued more executive orders than Republican presidents did between 1945 and 2016."
  },
  "unit": {
    "code": "2",
    "text": "2: Interactions Among Branches of Government"
  },
  "topic": {
    "code": "2.4",
    "text": "2.4: Roles and Powers of the President"
  },
  "skill": {
    "code": "Skill 3.B",
    "text": "Skill 3.B: Describe patterns and trends in data."
  }
}