{
  "id": "FT540347",
  "type": "mcq",
  "title": "Amsterdam as commercial center",
  "content": {
    "description": "",
    "question": "Which of the following cities dominated European trade and finance in the early seventeenth century?",
    "image": null,
    "choices": [
      {
        "label": "Venice",
        "image": null
      },
      {
        "label": "Paris",
        "image": null
      },
      {
        "label": "London",
        "image": null
      },
      {
        "label": "Amsterdam",
        "image": null
      },
      {
        "label": "Madrid",
        "image": null
      }
    ],
    "answer": "Amsterdam"
  },
  "unit": {
    "code": "3",
    "text": "3: Absolutism and Constitutionalism"
  },
  "topic": {
    "code": "3.5",
    "text": "3.5: Dutch Golden Age"
  },
  "skill": {
    "code": "Skill 1.A",
    "text": "Skill 1.A: Identify a historical concept, development, or process."
  }
}