{
  "id": "VH945179",
  "type": "mcq",
  "title": "Reed on expansion of Europe 1",
  "content": {
    "description": "",
    "question": "Which of the following general claims does the author make regarding the background of European overseas expansion?",
    "image": null,
    "choices": [
      {
        "label": "It was facilitated by states adopting a feudal governmental structure.",
        "image": null
      },
      {
        "label": "It was a result of the growth of the Habsburg Empire.",
        "image": null
      },
      {
        "label": "It was an outcome of the conflict between England and France.",
        "image": null
      },
      {
        "label": "It emerged from the consolidation of central governments.",
        "image": null
      }
    ],
    "answer": "It emerged from the consolidation of central governments."
  },
  "unit": {
    "code": "1",
    "text": "1: Renaissance and Exploration"
  },
  "topic": {
    "code": "1.7",
    "text": "1.7: Rivals on the World Stage"
  },
  "skill": {
    "code": "Skill 3.A",
    "text": "Skill 3.A: Identify and describe a claim and/or argument in a text-based or non-text-based source."
  }
}