{
  "id": "FT547936",
  "type": "mcq",
  "title": "The Frog in the Swimming Pool - Lines 1-4 include",
  "content": {
    "description": "",
    "question": "Lines 1-4 (“A wet . . . cart”) incorporate all of the following EXCEPT",
    "image": null,
    "choices": [
      {
        "label": "unconventional verbs",
        "image": null
      },
      {
        "label": "regular meter",
        "image": null
      },
      {
        "label": "tactile imagery",
        "image": null
      },
      {
        "label": "metaphor",
        "image": null
      }
    ],
    "answer": "regular meter"
  },
  "unit": {
    "code": "5",
    "text": "5: Poetry II"
  },
  "skill": {
    "code": "Skill 3.C",
    "text": "Skill 3.C: Explain the function of structure in a text."
  }
}