{
  "id": "VH909813",
  "type": "mcq",
  "title": "Suburban housing context",
  "content": {
    "description": "",
    "question": "The ideas expressed in the advertisement overlook which of the following contexts that allowed for the expansion of new suburban housing developments in the 1950s?",
    "image": null,
    "choices": [
      {
        "label": "The sharp increase in birth rates after the war",
        "image": null
      },
      {
        "label": "The reliance on new roads and highways",
        "image": null
      },
      {
        "label": "The growth of income for middle-class families",
        "image": null
      },
      {
        "label": "The appeal of modern amenities to consumers",
        "image": null
      }
    ],
    "answer": "The reliance on new roads and highways"
  },
  "unit": {
    "code": "8",
    "text": "8: 1945-1980"
  },
  "topic": {
    "code": "8.4",
    "text": "8.4: Economy after 1945"
  },
  "skill": {
    "code": "Skill 2.C",
    "text": "Skill 2.C: Explain the significance of a source's point of view, purpose, historical situation, and/or audience, including how these might limit the use(s) of a source."
  }
}