{
  "id": "VH915972",
  "type": "mcq",
  "title": "Cold War policy",
  "content": {
    "description": "",
    "question": "The excerpts best support which of the following arguments about postwar United States foreign policy?",
    "image": null,
    "choices": [
      {
        "label": "Some Americans called for the United States to reduce tensions with the Soviet Union.",
        "image": null
      },
      {
        "label": "Fear of Soviet expansion led to greater United States international involvement.",
        "image": null
      },
      {
        "label": "The United States sought to recolonize countries that had gained independence.",
        "image": null
      },
      {
        "label": "Many Americans opposed the creation of new alliances in Europe.",
        "image": null
      }
    ],
    "answer": "Fear of Soviet expansion led to greater United States international involvement."
  },
  "unit": {
    "code": "8",
    "text": "8: 1945-1980"
  },
  "topic": {
    "code": "8.7",
    "text": "8.7: America as a World Power"
  },
  "skill": {
    "code": "Skill 3.C",
    "text": "Skill 3.C: Compare the arguments or main ideas of two sources."
  }
}