{
  "id": "ANB000001",
  "type": "mcq",
  "title": "Vocab - rumpere - Aen 8 650-651",
  "content": {
    "description": "Aspiceres, pontem auderet quia vellerevello, -ere: to tear down CoclesCocles, -itis, m.: Horatius Cocles (a Roman hero) \net fluviumfluvium, -i, n. = flumen, -inis vinclis innaretinno, -are: to swim in CloeliaCloelia, -ae, f.: Cloelia (a Roman heroine) ruptis.",
    "question": "In the sentence, what does ruptis mean?",
    "image": null,
    "choices": [
      {
        "label": "Abandoned",
        "image": null
      },
      {
        "label": "Broken",
        "image": null
      },
      {
        "label": "Considered",
        "image": null
      },
      {
        "label": "Received",
        "image": null
      }
    ],
    "answer": "Broken"
  },
  "unit": {
    "code": "5",
    "text": "5: Vergil's Aeneid, Excerpts from Books 4, 6, 7, 11, and 12"
  },
  "skill": {
    "code": "1.A",
    "text": "1.A: Identify the meaning of Latin words and phrases."
  }
}