{
  "id": "FT555147",
  "type": "frq",
  "title": "Refugee populations",
  "content": {
    "description": "In recent years, the number of refugees has been increasing. However, most refugees come from just a few countries.",
    "question": "Directions: You have 25 minutes to answer the following question. It is suggested that you take up to 5 minutes of this time to plan and outline your answer.\n\nDefine the term “refugee.”\n\nDiscuss ONE political, ONE social, and ONE environmental reason why refugees flee their country of origin.\n\nUsing the chart shown, select a country of origin; then identify and explain ONE reason why refugees have left the country.\n\nExplain TWO economic impacts that refugees can have on a receiving country.",
    "image": null,
    "frqParts": [
      {
        "text": "Directions: You have 25 minutes to answer the following question. It is suggested that you take up to 5 minutes of this time to plan and outline your answer.\n\nDefine the term “refugee.”\n\nDiscuss ONE political, ONE social, and ONE environmental reason why refugees flee their country of origin.\n\nUsing the chart shown, select a country of origin; then identify and explain ONE reason why refugees have left the country.\n\nExplain TWO economic impacts that refugees can have on a receiving country.",
        "image": null
      }
    ]
  },
  "unit": {
    "code": "2",
    "text": "2: Population Migration Patterns and Process"
  },
  "topic": {
    "code": "2.11",
    "text": "2.11: Forced and Voluntary Migration"
  },
  "skill": {
    "code": "Skill 1.A",
    "text": "Skill 1.A: Describe geographic concepts, processes, models, and theories."
  }
}