{
  "id": "FT547078",
  "type": "mcq",
  "title": "Cubist use of multiple viewpoints-Picasso Ma Jolie",
  "content": {
    "description": "",
    "question": "The work reflects the artist's interest in",
    "image": "https://cdn.jsdelivr.net/gh/hearingmeout/Images-Shard-1@latest/Art_History/75b8b53058a876dbd57e76d930fe68e7.png",
    "choices": [
      {
        "label": "dream imagery",
        "image": null
      },
      {
        "label": "spirituality",
        "image": null
      },
      {
        "label": "a single light source",
        "image": null
      },
      {
        "label": "multiple viewpoints",
        "image": null
      }
    ],
    "answer": "multiple viewpoints"
  },
  "unit": {
    "code": "4",
    "text": "4: Later Europe and Americas, 1750 - 1980 CE"
  },
  "topic": {
    "code": "4.1",
    "text": "4.1: Interactions Within and Across Cultures in Later European and American Art"
  },
  "skill": {
    "code": "Skill 2.B",
    "text": "Skill 2.B: Explain how the possible intent, purpose, and/or function shape the creation or meaning of a work of art (or group of related works of art)."
  }
}