{
  "id": "FT550953",
  "type": "mcq",
  "title": "Wright, Robie House-identify architect",
  "content": {
    "description": "Refer to the following illustration.",
    "question": "A key element in the work is the",
    "image": "https://cdn.jsdelivr.net/gh/hearingmeout/Images-Shard-1@latest/Art_History/6b2c1ab68e26a8f0485eed507f368bbf.png",
    "choices": [
      {
        "label": "reliance on an iron framework",
        "image": null
      },
      {
        "label": "relationship of the structure to the site",
        "image": null
      },
      {
        "label": "influence of Romanesque forms",
        "image": null
      },
      {
        "label": "use of glass curtain walls",
        "image": null
      }
    ],
    "answer": "relationship of the structure to the site"
  },
  "unit": {
    "code": "4",
    "text": "4: Later Europe and Americas, 1750 - 1980 CE"
  },
  "topic": {
    "code": "4.1",
    "text": "4.1: Interactions Within and Across Cultures in Later European and American Art"
  },
  "skill": {
    "code": "Skill 1.C",
    "text": "Skill 1.C: Explain how artistic decisions about form, style, materials, technique, and/or content shape a work of art (or group of related works of art)."
  }
}