{
  "id": "VR028338",
  "type": "mcq",
  "title": "Sister Cities 3",
  "content": {
    "description": "The writer wants to use an appropriate transitional word or phrase to introduce the evidence in sentence 5 (reproduced below).",
    "question": "Nevertheless, the English city of Bristol and the German city of Hanover formed a partnership in 1947, with Bristol shipping relief supplies to Hanover and Hanover sending musicians to perform in Bristol.Which version of the underlined text most effectively accomplishes this goal?",
    "image": null,
    "choices": [
      {
        "label": "(As it is now)",
        "image": null
      },
      {
        "label": "Earlier,",
        "image": null
      },
      {
        "label": "Therefore,",
        "image": null
      },
      {
        "label": "For example,",
        "image": null
      }
    ],
    "answer": "For example,"
  },
  "unit": {
    "code": "5",
    "text": "5"
  },
  "skill": {
    "code": "Skill 6.B",
    "text": "Skill 6.B: Use transitional elements to guide the reader through the line of reasoning of an argument."
  }
}