{
  "id": "IX706965",
  "type": "mcq",
  "title": "Processes - Numerical Derivative",
  "content": {
    "description": "",
    "question": "Let <math alttext=\"f\" display=\"inline\" overflow=\"scroll\"><mstyle><mrow><mi>f</mi></mrow></mstyle></math> be the function given by <math alttext=\"f of x equals, x cubed, plus 3 times x squared, minus 4\" display=\"inline\" overflow=\"scroll\"><mstyle><mrow><mi>f</mi><mrow><mo>(</mo><mi>x</mi><mo>)</mo></mrow><mo>=</mo><msup><mrow><mi>x</mi></mrow><mrow><mn>3</mn></mrow></msup><mo>+</mo><mn>3</mn><msup><mrow><mi>x</mi></mrow><mrow><mn>2</mn></mrow></msup><mo>−</mo><mn>4</mn></mrow></mstyle></math>. What is the value of <math alttext=\"f prime of 2\" display=\"inline\" overflow=\"scroll\"><mrow><msup><mrow><mi>f</mi></mrow><mrow><mo>′</mo></mrow></msup><mrow><mo>(</mo><mn>2</mn><mo>)</mo></mrow></mrow></math> ?",
    "image": null,
    "choices": [
      {
        "label": "48",
        "image": null
      },
      {
        "label": "24",
        "image": null
      },
      {
        "label": "20",
        "image": null
      },
      {
        "label": "10",
        "image": null
      }
    ],
    "answer": "24"
  },
  "unit": {
    "code": "2",
    "text": "2: Differentiation: Definition and Fundamental Properties"
  },
  "topic": {
    "code": "2.6",
    "text": "2.6: Derivative Rules - Constant, Sum, Difference, and Constant Multiple"
  },
  "skill": {
    "code": "Skill 1.E",
    "text": "Skill 1.E: Apply appropriate mathematical rules or procedures, with and without technology."
  }
}