{
  "id": "ZC723854",
  "type": "mcq",
  "title": "Limit of piecewise function",
  "content": {
    "description": "",
    "question": "is",
    "image": "https://ap.oly.st/images/57097714816eb565430d984722397a6a.PNG",
    "choices": [
      {
        "label": "ln2",
        "image": null
      },
      {
        "label": "ln8",
        "image": null
      },
      {
        "label": "ln16",
        "image": null
      },
      {
        "label": "4",
        "image": null
      },
      {
        "label": "nonexistent",
        "image": null
      }
    ],
    "answer": "nonexistent"
  },
  "unit": {
    "code": "1",
    "text": "1: Limits and Continuity"
  },
  "topic": {
    "code": "1.5",
    "text": "1.5: Determining Limits Using Algebraic Properties of Limits"
  },
  "skill": {
    "code": "Skill 1.E",
    "text": "Skill 1.E: Apply appropriate mathematical rules or procedures, with and without technology."
  }
}