{
  "id": "VH925555",
  "type": "mcq",
  "title": "Grave",
  "content": {
    "description": "",
    "question": "The tempo marking above the score indicates that the excerpt should be performed at a",
    "image": "https://ap.oly.st/images/fa5feee803dba906f688060568fc45a4.png",
    "choices": [
      {
        "label": "slow solemn tempo",
        "image": null
      },
      {
        "label": "moderately slow tempo",
        "image": null
      },
      {
        "label": "moderately fast tempo",
        "image": null
      },
      {
        "label": "fast lively tempo",
        "image": null
      }
    ],
    "answer": "slow solemn tempo"
  },
  "unit": {
    "code": "1",
    "text": "1: Music Fundamentals I - Pitch, Major Scales and Key Signatures, Rhythm, Meter, and Expressive Elements"
  },
  "topic": {
    "code": "1.9",
    "text": "1.9: Tempo"
  },
  "skill": {
    "code": "Skill 2.G",
    "text": "Skill 2.G: Use terms and symbols to describe aspects of musical design in notated music, including texture, timbre, and instrumentation, and expressive elements, including dynamics, articulation, and tempo."
  }
}