{
  "id": "VH944242",
  "type": "mcq",
  "title": "close and open spacing",
  "content": {
    "description": "",
    "question": "Which of the following statements accurately describes the texture?",
    "image": "https://cdn.jsdelivr.net/gh/hearingmeout/Images-Shard-2@latest/Music_Theory/1a9beb6a823994e110c43f8b8d024317.png",
    "choices": [
      {
        "label": "The excerpt uses close spacing throughout.",
        "image": null
      },
      {
        "label": "The excerpt uses open spacing throughout.",
        "image": null
      },
      {
        "label": "The excerpt uses open spacing at the beginning and close spacing at the end.",
        "image": null
      },
      {
        "label": "The excerpt uses close spacing at the beginning and open spacing at the end.",
        "image": null
      }
    ],
    "answer": "The excerpt uses close spacing at the beginning and open spacing at the end."
  },
  "unit": {
    "code": "2",
    "text": "2: Music Fundamentals II - Minor Scales and Key Signatures, Melody, Timbre, and Texture"
  },
  "topic": {
    "code": "2.11",
    "text": "2.11: Texture and Texture Types"
  },
  "skill": {
    "code": "Skill 2.G",
    "text": "Skill 2.G: Use terms and symbols to describe aspects of musical design in notated music, including texture, timbre, and instrumentation, and expressive elements, including dynamics, articulation, and tempo."
  }
}