{
  "id": "VH991291",
  "type": "mcq",
  "title": "Beethoven Violin Sonata trills and appoggiaturas",
  "content": {
    "description": "",
    "question": "Listen to the excerpt.\n\nThe main melodic motive, repeated several times in both the violin and piano, features which of the following types of ornaments?",
    "image": null,
    "choices": [
      {
        "label": "Trills",
        "image": null
      },
      {
        "label": "Lower neighbor tones",
        "image": null
      },
      {
        "label": "Unaccented passing tones",
        "image": null
      },
      {
        "label": "Ascending passing tones",
        "image": null
      }
    ],
    "answer": "Trills"
  },
  "unit": {
    "code": "6",
    "text": "6: Harmony and Voice Leading III - Embellishments, Motives, and Melodic Devices"
  },
  "topic": {
    "code": "6.1",
    "text": "6.1: Embellishing Tones - Identifying Passing Tones and Neighbor Tones"
  },
  "skill": {
    "code": "Skill 1.A",
    "text": "Skill 1.A: Use symbols and terms to describe features of pitch in performed music, including pitch patterns and relationships, melodic features, chords, harmonic progressions, and cadences."
  }
}