{
  "id": "FT545426",
  "type": "mcq",
  "title": "Find internal resistance of battery",
  "content": {
    "description": "",
    "question": "A 30-ohm resistor and a 60-ohm resistor are connected as shown above to a battery of emf 20 volts and internal resistance r. The current in the circuit is 0.8 ampere. What is the value of r ?",
    "image": "https://ap.oly.st/images/25963393e7f9fb616f0a0a974f2effc9.png",
    "choices": [
      {
        "label": "0.22 ğ›€",
        "image": null
      },
      {
        "label": "4.5 ğ›€",
        "image": null
      },
      {
        "label": "5 ğ›€",
        "image": null
      },
      {
        "label": "16 ğ›€",
        "image": null
      },
      {
        "label": "70 ğ›€",
        "image": null
      }
    ],
    "answer": "5 ğ›€"
  },
  "unit": {
    "code": "11",
    "text": "11: Electric Circuits"
  },
  "topic": {
    "code": "11.3",
    "text": "11.3: Resistance, Resistivity, and Ohm's Law"
  },
  "skill": {
    "code": "2.B",
    "text": "2.B: Calculate or estimate an unknown quantity with units from known quantities, by selecting and following a logical computational pathway."
  }
}