{
  "id": "VR733325",
  "type": "mcq",
  "title": "An Englishman in Japan 1611 Q2",
  "content": {
    "description": "",
    "question": "Which of the following developments in the period 1450–1750 best explains the conflicts referred to in the passage?",
    "image": null,
    "choices": [
      {
        "label": "Imperial expansion in Africa",
        "image": null
      },
      {
        "label": "Competition for trade in Asia",
        "image": null
      },
      {
        "label": "Expansion of the Mughal Empire",
        "image": null
      },
      {
        "label": "Piracy in the East China Sea",
        "image": null
      }
    ],
    "answer": "Competition for trade in Asia"
  },
  "unit": {
    "code": "4",
    "text": "4: Transoceanic Interconnections"
  },
  "topic": {
    "code": "4.4",
    "text": "4.4: Maritime Empires Established"
  },
  "skill": {
    "code": "Skill 4.B",
    "text": "Skill 4.B: Explain how a specific historical development or process is situated within a broader historical context."
  }
}