{
  "id": "FT549162",
  "type": "frq",
  "title": "Optimization involving area part - c",
  "content": null,
  "unit": {
    "code": "5",
    "text": "5: Analytical Applications of Differentiation"
  },
  "topic": {
    "code": "5.4",
    "text": "5.4: Using the First Derivative Test to Determine Relative (Local) Extrema"
  },
  "skill": {
    "code": "Skill 4.C",
    "text": "Skill 4.C: Use appropriate mathematical symbols and notation (e.g., Represent a derivative using ƒ'(x), y', and dy/dx)."
  }
}