{
  "id": "FT536565",
  "type": "mcq",
  "title": "Environmental impact of human population",
  "content": {
    "description": "",
    "question": "Which of the following would most likely have the greatest positive impact on the quality of the natural environment worldwide?",
    "image": null,
    "choices": [
      {
        "label": "Discovery of new reserves of fossil fuel in coastal areas",
        "image": null
      },
      {
        "label": "Increased agricultural production on marginal desert lands",
        "image": null
      },
      {
        "label": "Increased life expectancy in more developed nations",
        "image": null
      },
      {
        "label": "Increased reliance on food from ocean ecosystems",
        "image": null
      },
      {
        "label": "Stabilization or reduction of the size of the human population",
        "image": null
      }
    ],
    "answer": "Stabilization or reduction of the size of the human population"
  },
  "unit": {
    "code": "9",
    "text": "9: Global Change"
  },
  "topic": {
    "code": "9.10",
    "text": "9.10: Human Impacts on Biodiversity"
  },
  "skill": {
    "code": "Skill 7.B",
    "text": "Skill 7.B: Describe potential responses or approaches to environmental problems."
  }
}