{
  "id": "FT543558",
  "type": "mcq",
  "title": "Expansionary fiscal, tight money drive up i rates",
  "content": {
    "description": "",
    "question": "A stimulative fiscal policy combined with a restrictive monetary policy will necessarily cause",
    "image": null,
    "choices": [
      {
        "label": "gross domestic product to increase",
        "image": null
      },
      {
        "label": "gross domestic product to decrease",
        "image": null
      },
      {
        "label": "interest rates to fall",
        "image": null
      },
      {
        "label": "interest rates to rise",
        "image": null
      },
      {
        "label": "the federal budget deficit to decrease",
        "image": null
      }
    ],
    "answer": "interest rates to rise"
  },
  "unit": {
    "code": "5",
    "text": "5: Long-Run Consequences of Stabilization Policies"
  },
  "topic": {
    "code": "5.1",
    "text": "5.1: Fiscal and Monetary Policy Actions in the Short Run"
  },
  "skill": {
    "code": "Skill 3.B",
    "text": "Skill 3.B: Determine the effect(s) of one or more changes on other economic markets."
  }
}