{
  "id": "FT5654",
  "type": "mcq",
  "title": "Mughal mosque built by Akbar and syncretism",
  "content": {
    "description": "",
    "question": "The photograph above of a sixteenth-century Mughal mosque in India built by Akbar is an example of which of the following?",
    "image": null,
    "choices": [
      {
        "label": "Emergence of capitalist economies",
        "image": null
      },
      {
        "label": "Expansion of coercive labor systems",
        "image": null
      },
      {
        "label": "Creation of a global trade network",
        "image": null
      },
      {
        "label": "Cultural syncretism",
        "image": null
      }
    ],
    "answer": "Cultural syncretism"
  },
  "unit": {
    "code": "3",
    "text": "3: Land-Based Empires"
  },
  "topic": {
    "code": "3.2",
    "text": "3.2: Empires - Administration"
  },
  "skill": {
    "code": "Skill 1.A",
    "text": "Skill 1.A: Identify a historical concept, development, or process."
  }
}