{
  "id": "FT535553",
  "type": "mcq",
  "title": "Changing currency - Jean's problem",
  "content": {
    "description": "You will now listen to a dialogue. Afterwards, you will be asked several questions about what you have just heard. Select the best answer to each question from among the four choices. Now listen to the dialogue.",
    "question": "",
    "image": null,
    "choices": [
      {
        "label": "Il ne connaît pas très bien la ville.",
        "image": null
      },
      {
        "label": "Il a manqué un rendez-vous.",
        "image": null
      },
      {
        "label": "Il a dépensé trop d’argent dans la boutique.",
        "image": null
      },
      {
        "label": "Il n’a pas l’argent du pays qu'il visite.",
        "image": null
      }
    ],
    "answer": "Il n’a pas l’argent du pays qu'il visite."
  },
  "unit": {
    "code": "5",
    "text": "5: Factors That Affect the Quality of Life"
  },
  "skill": {
    "code": "Skill 1.A",
    "text": "Skill 1.A: Describe the literal meaning of the text."
  }
}