{
  "id": "VR100476",
  "type": "mcq",
  "title": "Location of the event",
  "content": {
    "description": "",
    "question": "What does the article say about the location where the event was held?",
    "image": null,
    "choices": [
      {
        "label": "The venue is famous for its pure natural scenery and wildlife.",
        "image": null
      },
      {
        "label": "Its location is famous but not suitable for attracting large numbers of visitors.",
        "image": null
      },
      {
        "label": "It has clear lake water, beautiful flowers, and unusual stones.",
        "image": null
      },
      {
        "label": "It demonstrates the city’s efforts to preserve traditional Chinese culture.",
        "image": null
      }
    ],
    "answer": "It has clear lake water, beautiful flowers, and unusual stones."
  },
  "unit": {
    "code": "3",
    "text": "3: Influences of Beauty and Art"
  },
  "skill": {
    "code": "Skill 2.A",
    "text": "Skill 2.A: Make connections among cultural and interdisciplinary information provided in texts."
  }
}