{
  "id": "FT536659",
  "type": "mcq",
  "title": "Identify three sided figure as a triangle",
  "content": {
    "description": "",
    "question": "The tendency of most people to identify a three-sided figure as a triangle, even when one of its sides is incomplete, is the result of a perceptual process known as",
    "image": null,
    "choices": [
      {
        "label": "closure",
        "image": null
      },
      {
        "label": "similarity",
        "image": null
      },
      {
        "label": "feature analysis",
        "image": null
      },
      {
        "label": "shape constancy",
        "image": null
      }
    ],
    "answer": "closure"
  },
  "unit": {
    "code": "2",
    "text": "2: Cognition"
  },
  "topic": {
    "code": "2.1",
    "text": "2.1: Perception"
  },
  "skill": {
    "code": "1.A",
    "text": "1.A: Apply psychological perspectives, theories, concepts, and research findings to a scenario."
  }
}