{
  "id": "VR841800",
  "type": "mcq",
  "title": "Random Assignment-Explicit Implicit Memories",
  "content": {
    "description": "",
    "question": "Researchers want to examine if there is a difference between the retention of implicit versus explicit memories. To conduct this research as an experiment, which of the following would be necessary?",
    "image": null,
    "choices": [
      {
        "label": "Statistical Significance",
        "image": null
      },
      {
        "label": "Random Assignment",
        "image": null
      },
      {
        "label": "Random Selection",
        "image": null
      },
      {
        "label": "Correlation Coefficient",
        "image": null
      }
    ],
    "answer": "Random Assignment"
  },
  "unit": {
    "code": "2",
    "text": "2: Cognition"
  },
  "topic": {
    "code": "2.3",
    "text": "2.3: Introduction to Memory"
  },
  "skill": {
    "code": "2.A",
    "text": "2.A: Determine the type of research design(s) used in a given study."
  }
}