{
  "id": "FT548289",
  "type": "mcq",
  "title": "Vanity Fair - Sir Pitt's attitude and behavior",
  "content": {
    "description": "",
    "question": "The narrator attributes Sir Pitt's attitude and behavior to which of the following factors?",
    "image": null,
    "choices": [
      {
        "label": "Lack of formal education",
        "image": null
      },
      {
        "label": "Absence of religious beliefs",
        "image": null
      },
      {
        "label": "Traits of his ancestors",
        "image": null
      },
      {
        "label": "Social rank and flawed character",
        "image": null
      }
    ],
    "answer": "Social rank and flawed character"
  },
  "unit": {
    "code": "4",
    "text": "4: Short Fiction II"
  },
  "skill": {
    "code": "Skill 4.C",
    "text": "Skill 4.C: Identify and describe details, diction, or syntax in a text that reveal a narrator's or speaker's perspective."
  }
}